{
  "id": "d9410619-2785-4ee5-9ad5-3f4d209d0a00",
  "prevId": "e51f3994-a316-473a-9e34-57199ce1cf84",
  "version": "7",
  "dialect": "postgresql",
  "tables": {
    "public.analyst_estimates": {
      "name": "analyst_estimates",
      "schema": "",
      "columns": {
        "symbol": {
          "name": "symbol",
          "type": "text",
          "primaryKey": false,
          "notNull": true
        },
        "period": {
          "name": "period",
          "type": "text",
          "primaryKey": false,
          "notNull": true
        },
        "fiscal_date": {
          "name": "fiscal_date",
          "type": "date",
          "primaryKey": false,
          "notNull": true
        },
        "known_at": {
          "name": "known_at",
          "type": "timestamp with time zone",
          "primaryKey": false,
          "notNull": true
        },
        "data": {
          "name": "data",
          "type": "jsonb",
          "primaryKey": false,
          "notNull": true
        }
      },
      "indexes": {},
      "foreignKeys": {},
      "compositePrimaryKeys": {
        "analyst_estimates_symbol_period_fiscal_date_pk": {
          "name": "analyst_estimates_symbol_period_fiscal_date_pk",
          "columns": [
            "symbol",
            "period",
            "fiscal_date"
          ]
        }
      },
      "uniqueConstraints": {},
      "policies": {},
      "checkConstraints": {},
      "isRLSEnabled": false
    },
    "public.balance_sheet": {
      "name": "balance_sheet",
      "schema": "",
      "columns": {
        "symbol": {
          "name": "symbol",
          "type": "text",
          "primaryKey": false,
          "notNull": true
        },
        "period": {
          "name": "period",
          "type": "text",
          "primaryKey": false,
          "notNull": true
        },
        "fiscal_date": {
          "name": "fiscal_date",
          "type": "date",
          "primaryKey": false,
          "notNull": true
        },
        "known_at": {
          "name": "known_at",
          "type": "timestamp with time zone",
          "primaryKey": false,
          "notNull": true
        },
        "data": {
          "name": "data",
          "type": "jsonb",
          "primaryKey": false,
          "notNull": true
        }
      },
      "indexes": {},
      "foreignKeys": {},
      "compositePrimaryKeys": {
        "balance_sheet_symbol_period_fiscal_date_pk": {
          "name": "balance_sheet_symbol_period_fiscal_date_pk",
          "columns": [
            "symbol",
            "period",
            "fiscal_date"
          ]
        }
      },
      "uniqueConstraints": {},
      "policies": {},
      "checkConstraints": {},
      "isRLSEnabled": false
    },
    "public.cash_flow": {
      "name": "cash_flow",
      "schema": "",
      "columns": {
        "symbol": {
          "name": "symbol",
          "type": "text",
          "primaryKey": false,
          "notNull": true
        },
        "period": {
          "name": "period",
          "type": "text",
          "primaryKey": false,
          "notNull": true
        },
        "fiscal_date": {
          "name": "fiscal_date",
          "type": "date",
          "primaryKey": false,
          "notNull": true
        },
        "known_at": {
          "name": "known_at",
          "type": "timestamp with time zone",
          "primaryKey": false,
          "notNull": true
        },
        "data": {
          "name": "data",
          "type": "jsonb",
          "primaryKey": false,
          "notNull": true
        }
      },
      "indexes": {},
      "foreignKeys": {},
      "compositePrimaryKeys": {
        "cash_flow_symbol_period_fiscal_date_pk": {
          "name": "cash_flow_symbol_period_fiscal_date_pk",
          "columns": [
            "symbol",
            "period",
            "fiscal_date"
          ]
        }
      },
      "uniqueConstraints": {},
      "policies": {},
      "checkConstraints": {},
      "isRLSEnabled": false
    },
    "public.daily_prices": {
      "name": "daily_prices",
      "schema": "",
      "columns": {
        "symbol": {
          "name": "symbol",
          "type": "text",
          "primaryKey": false,
          "notNull": true
        },
        "trade_date": {
          "name": "trade_date",
          "type": "date",
          "primaryKey": false,
          "notNull": true
        },
        "open": {
          "name": "open",
          "type": "double precision",
          "primaryKey": false,
          "notNull": false
        },
        "high": {
          "name": "high",
          "type": "double precision",
          "primaryKey": false,
          "notNull": false
        },
        "low": {
          "name": "low",
          "type": "double precision",
          "primaryKey": false,
          "notNull": false
        },
        "close": {
          "name": "close",
          "type": "double precision",
          "primaryKey": false,
          "notNull": false
        },
        "adj_close": {
          "name": "adj_close",
          "type": "double precision",
          "primaryKey": false,
          "notNull": false
        },
        "volume": {
          "name": "volume",
          "type": "bigint",
          "primaryKey": false,
          "notNull": false
        }
      },
      "indexes": {
        "idx_prices_symbol_date": {
          "name": "idx_prices_symbol_date",
          "columns": [
            {
              "expression": "symbol",
              "isExpression": false,
              "asc": true,
              "nulls": "last"
            },
            {
              "expression": "trade_date",
              "isExpression": false,
              "asc": true,
              "nulls": "last"
            }
          ],
          "isUnique": false,
          "concurrently": false,
          "method": "btree",
          "with": {}
        }
      },
      "foreignKeys": {},
      "compositePrimaryKeys": {
        "daily_prices_symbol_trade_date_pk": {
          "name": "daily_prices_symbol_trade_date_pk",
          "columns": [
            "symbol",
            "trade_date"
          ]
        }
      },
      "uniqueConstraints": {},
      "policies": {},
      "checkConstraints": {},
      "isRLSEnabled": false
    },
    "public.events": {
      "name": "events",
      "schema": "",
      "columns": {
        "id": {
          "name": "id",
          "type": "text",
          "primaryKey": true,
          "notNull": true
        },
        "source": {
          "name": "source",
          "type": "text",
          "primaryKey": false,
          "notNull": true
        },
        "external_id": {
          "name": "external_id",
          "type": "text",
          "primaryKey": false,
          "notNull": true
        },
        "symbol": {
          "name": "symbol",
          "type": "text",
          "primaryKey": false,
          "notNull": false
        },
        "event_type": {
          "name": "event_type",
          "type": "text",
          "primaryKey": false,
          "notNull": false
        },
        "direction_hint": {
          "name": "direction_hint",
          "type": "text",
          "primaryKey": false,
          "notNull": false
        },
        "headline": {
          "name": "headline",
          "type": "text",
          "primaryKey": false,
          "notNull": false
        },
        "raw": {
          "name": "raw",
          "type": "jsonb",
          "primaryKey": false,
          "notNull": false
        },
        "observed_at": {
          "name": "observed_at",
          "type": "timestamp with time zone",
          "primaryKey": false,
          "notNull": false
        },
        "ingested_at": {
          "name": "ingested_at",
          "type": "timestamp with time zone",
          "primaryKey": false,
          "notNull": true,
          "default": "now()"
        },
        "delivery_status": {
          "name": "delivery_status",
          "type": "text",
          "primaryKey": false,
          "notNull": true,
          "default": "'pending'"
        },
        "delivery_attempts": {
          "name": "delivery_attempts",
          "type": "integer",
          "primaryKey": false,
          "notNull": true,
          "default": 0
        },
        "last_error": {
          "name": "last_error",
          "type": "text",
          "primaryKey": false,
          "notNull": false
        }
      },
      "indexes": {
        "uq_events_source_external": {
          "name": "uq_events_source_external",
          "columns": [
            {
              "expression": "source",
              "isExpression": false,
              "asc": true,
              "nulls": "last"
            },
            {
              "expression": "external_id",
              "isExpression": false,
              "asc": true,
              "nulls": "last"
            }
          ],
          "isUnique": true,
          "concurrently": false,
          "method": "btree",
          "with": {}
        },
        "idx_events_delivery": {
          "name": "idx_events_delivery",
          "columns": [
            {
              "expression": "delivery_status",
              "isExpression": false,
              "asc": true,
              "nulls": "last"
            }
          ],
          "isUnique": false,
          "concurrently": false,
          "method": "btree",
          "with": {}
        }
      },
      "foreignKeys": {},
      "compositePrimaryKeys": {},
      "uniqueConstraints": {},
      "policies": {},
      "checkConstraints": {},
      "isRLSEnabled": false
    },
    "public.feedback_notes": {
      "name": "feedback_notes",
      "schema": "",
      "columns": {
        "id": {
          "name": "id",
          "type": "text",
          "primaryKey": true,
          "notNull": true
        },
        "signal_id": {
          "name": "signal_id",
          "type": "text",
          "primaryKey": false,
          "notNull": false
        },
        "symbol": {
          "name": "symbol",
          "type": "text",
          "primaryKey": false,
          "notNull": false
        },
        "event_type": {
          "name": "event_type",
          "type": "text",
          "primaryKey": false,
          "notNull": false
        },
        "lesson": {
          "name": "lesson",
          "type": "text",
          "primaryKey": false,
          "notNull": true
        },
        "scores": {
          "name": "scores",
          "type": "jsonb",
          "primaryKey": false,
          "notNull": false
        },
        "created_at": {
          "name": "created_at",
          "type": "timestamp with time zone",
          "primaryKey": false,
          "notNull": true,
          "default": "now()"
        }
      },
      "indexes": {
        "idx_feedback_symbol": {
          "name": "idx_feedback_symbol",
          "columns": [
            {
              "expression": "symbol",
              "isExpression": false,
              "asc": true,
              "nulls": "last"
            }
          ],
          "isUnique": false,
          "concurrently": false,
          "method": "btree",
          "with": {}
        },
        "idx_feedback_event_type": {
          "name": "idx_feedback_event_type",
          "columns": [
            {
              "expression": "event_type",
              "isExpression": false,
              "asc": true,
              "nulls": "last"
            }
          ],
          "isUnique": false,
          "concurrently": false,
          "method": "btree",
          "with": {}
        }
      },
      "foreignKeys": {},
      "compositePrimaryKeys": {},
      "uniqueConstraints": {},
      "policies": {},
      "checkConstraints": {},
      "isRLSEnabled": false
    },
    "public.financial_ratios": {
      "name": "financial_ratios",
      "schema": "",
      "columns": {
        "symbol": {
          "name": "symbol",
          "type": "text",
          "primaryKey": false,
          "notNull": true
        },
        "period": {
          "name": "period",
          "type": "text",
          "primaryKey": false,
          "notNull": true
        },
        "fiscal_date": {
          "name": "fiscal_date",
          "type": "date",
          "primaryKey": false,
          "notNull": true
        },
        "known_at": {
          "name": "known_at",
          "type": "timestamp with time zone",
          "primaryKey": false,
          "notNull": true
        },
        "data": {
          "name": "data",
          "type": "jsonb",
          "primaryKey": false,
          "notNull": true
        }
      },
      "indexes": {},
      "foreignKeys": {},
      "compositePrimaryKeys": {
        "financial_ratios_symbol_period_fiscal_date_pk": {
          "name": "financial_ratios_symbol_period_fiscal_date_pk",
          "columns": [
            "symbol",
            "period",
            "fiscal_date"
          ]
        }
      },
      "uniqueConstraints": {},
      "policies": {},
      "checkConstraints": {},
      "isRLSEnabled": false
    },
    "public.income_statement": {
      "name": "income_statement",
      "schema": "",
      "columns": {
        "symbol": {
          "name": "symbol",
          "type": "text",
          "primaryKey": false,
          "notNull": true
        },
        "period": {
          "name": "period",
          "type": "text",
          "primaryKey": false,
          "notNull": true
        },
        "fiscal_date": {
          "name": "fiscal_date",
          "type": "date",
          "primaryKey": false,
          "notNull": true
        },
        "known_at": {
          "name": "known_at",
          "type": "timestamp with time zone",
          "primaryKey": false,
          "notNull": true
        },
        "data": {
          "name": "data",
          "type": "jsonb",
          "primaryKey": false,
          "notNull": true
        }
      },
      "indexes": {},
      "foreignKeys": {},
      "compositePrimaryKeys": {
        "income_statement_symbol_period_fiscal_date_pk": {
          "name": "income_statement_symbol_period_fiscal_date_pk",
          "columns": [
            "symbol",
            "period",
            "fiscal_date"
          ]
        }
      },
      "uniqueConstraints": {},
      "policies": {},
      "checkConstraints": {},
      "isRLSEnabled": false
    },
    "public.logs": {
      "name": "logs",
      "schema": "",
      "columns": {
        "id": {
          "name": "id",
          "type": "text",
          "primaryKey": true,
          "notNull": true
        },
        "ts": {
          "name": "ts",
          "type": "timestamp with time zone",
          "primaryKey": false,
          "notNull": true,
          "default": "now()"
        },
        "level": {
          "name": "level",
          "type": "text",
          "primaryKey": false,
          "notNull": true
        },
        "service": {
          "name": "service",
          "type": "text",
          "primaryKey": false,
          "notNull": true
        },
        "event": {
          "name": "event",
          "type": "text",
          "primaryKey": false,
          "notNull": true
        },
        "symbol": {
          "name": "symbol",
          "type": "text",
          "primaryKey": false,
          "notNull": false
        },
        "external_id": {
          "name": "external_id",
          "type": "text",
          "primaryKey": false,
          "notNull": false
        },
        "notification_id": {
          "name": "notification_id",
          "type": "text",
          "primaryKey": false,
          "notNull": false
        },
        "signal_id": {
          "name": "signal_id",
          "type": "text",
          "primaryKey": false,
          "notNull": false
        },
        "fields": {
          "name": "fields",
          "type": "jsonb",
          "primaryKey": false,
          "notNull": false
        }
      },
      "indexes": {
        "idx_logs_ts": {
          "name": "idx_logs_ts",
          "columns": [
            {
              "expression": "ts",
              "isExpression": false,
              "asc": true,
              "nulls": "last"
            }
          ],
          "isUnique": false,
          "concurrently": false,
          "method": "btree",
          "with": {}
        },
        "idx_logs_service_ts": {
          "name": "idx_logs_service_ts",
          "columns": [
            {
              "expression": "service",
              "isExpression": false,
              "asc": true,
              "nulls": "last"
            },
            {
              "expression": "ts",
              "isExpression": false,
              "asc": true,
              "nulls": "last"
            }
          ],
          "isUnique": false,
          "concurrently": false,
          "method": "btree",
          "with": {}
        },
        "idx_logs_level": {
          "name": "idx_logs_level",
          "columns": [
            {
              "expression": "level",
              "isExpression": false,
              "asc": true,
              "nulls": "last"
            }
          ],
          "isUnique": false,
          "concurrently": false,
          "method": "btree",
          "with": {}
        },
        "idx_logs_symbol": {
          "name": "idx_logs_symbol",
          "columns": [
            {
              "expression": "symbol",
              "isExpression": false,
              "asc": true,
              "nulls": "last"
            }
          ],
          "isUnique": false,
          "concurrently": false,
          "method": "btree",
          "with": {}
        }
      },
      "foreignKeys": {},
      "compositePrimaryKeys": {},
      "uniqueConstraints": {},
      "policies": {},
      "checkConstraints": {},
      "isRLSEnabled": false
    },
    "public.notifications": {
      "name": "notifications",
      "schema": "",
      "columns": {
        "id": {
          "name": "id",
          "type": "text",
          "primaryKey": true,
          "notNull": true
        },
        "source": {
          "name": "source",
          "type": "text",
          "primaryKey": false,
          "notNull": true
        },
        "batch_key": {
          "name": "batch_key",
          "type": "text",
          "primaryKey": false,
          "notNull": true
        },
        "symbol": {
          "name": "symbol",
          "type": "text",
          "primaryKey": false,
          "notNull": true
        },
        "event_type": {
          "name": "event_type",
          "type": "text",
          "primaryKey": false,
          "notNull": true
        },
        "event_ids": {
          "name": "event_ids",
          "type": "jsonb",
          "primaryKey": false,
          "notNull": true
        },
        "count": {
          "name": "count",
          "type": "integer",
          "primaryKey": false,
          "notNull": true
        },
        "summary": {
          "name": "summary",
          "type": "text",
          "primaryKey": false,
          "notNull": false
        },
        "observed_at": {
          "name": "observed_at",
          "type": "timestamp with time zone",
          "primaryKey": false,
          "notNull": false
        },
        "ingested_at": {
          "name": "ingested_at",
          "type": "timestamp with time zone",
          "primaryKey": false,
          "notNull": true,
          "default": "now()"
        },
        "status": {
          "name": "status",
          "type": "text",
          "primaryKey": false,
          "notNull": true,
          "default": "'pending'"
        },
        "delivery_status": {
          "name": "delivery_status",
          "type": "text",
          "primaryKey": false,
          "notNull": true,
          "default": "'pending'"
        },
        "delivery_attempts": {
          "name": "delivery_attempts",
          "type": "integer",
          "primaryKey": false,
          "notNull": true,
          "default": 0
        },
        "last_error": {
          "name": "last_error",
          "type": "text",
          "primaryKey": false,
          "notNull": false
        }
      },
      "indexes": {
        "uq_notifications_source_batch": {
          "name": "uq_notifications_source_batch",
          "columns": [
            {
              "expression": "source",
              "isExpression": false,
              "asc": true,
              "nulls": "last"
            },
            {
              "expression": "batch_key",
              "isExpression": false,
              "asc": true,
              "nulls": "last"
            }
          ],
          "isUnique": true,
          "concurrently": false,
          "method": "btree",
          "with": {}
        },
        "idx_notifications_delivery": {
          "name": "idx_notifications_delivery",
          "columns": [
            {
              "expression": "delivery_status",
              "isExpression": false,
              "asc": true,
              "nulls": "last"
            }
          ],
          "isUnique": false,
          "concurrently": false,
          "method": "btree",
          "with": {}
        },
        "idx_notifications_status": {
          "name": "idx_notifications_status",
          "columns": [
            {
              "expression": "status",
              "isExpression": false,
              "asc": true,
              "nulls": "last"
            }
          ],
          "isUnique": false,
          "concurrently": false,
          "method": "btree",
          "with": {}
        }
      },
      "foreignKeys": {},
      "compositePrimaryKeys": {},
      "uniqueConstraints": {},
      "policies": {},
      "checkConstraints": {},
      "isRLSEnabled": false
    },
    "public.positions": {
      "name": "positions",
      "schema": "",
      "columns": {
        "signal_id": {
          "name": "signal_id",
          "type": "text",
          "primaryKey": true,
          "notNull": true
        },
        "symbol": {
          "name": "symbol",
          "type": "text",
          "primaryKey": false,
          "notNull": true
        },
        "direction": {
          "name": "direction",
          "type": "text",
          "primaryKey": false,
          "notNull": true
        },
        "status": {
          "name": "status",
          "type": "text",
          "primaryKey": false,
          "notNull": true,
          "default": "'open'"
        },
        "target_weight": {
          "name": "target_weight",
          "type": "double precision",
          "primaryKey": false,
          "notNull": false
        },
        "target_notional": {
          "name": "target_notional",
          "type": "double precision",
          "primaryKey": false,
          "notNull": false
        },
        "entry_price": {
          "name": "entry_price",
          "type": "double precision",
          "primaryKey": false,
          "notNull": false
        },
        "shares": {
          "name": "shares",
          "type": "double precision",
          "primaryKey": false,
          "notNull": false
        },
        "sector_at_entry": {
          "name": "sector_at_entry",
          "type": "text",
          "primaryKey": false,
          "notNull": false
        },
        "sizing_reasons": {
          "name": "sizing_reasons",
          "type": "jsonb",
          "primaryKey": false,
          "notNull": false
        },
        "sizing_params": {
          "name": "sizing_params",
          "type": "jsonb",
          "primaryKey": false,
          "notNull": false
        },
        "closed_at": {
          "name": "closed_at",
          "type": "timestamp with time zone",
          "primaryKey": false,
          "notNull": false
        },
        "exit_price": {
          "name": "exit_price",
          "type": "double precision",
          "primaryKey": false,
          "notNull": false
        },
        "realized_return": {
          "name": "realized_return",
          "type": "double precision",
          "primaryKey": false,
          "notNull": false
        },
        "opened_at": {
          "name": "opened_at",
          "type": "timestamp with time zone",
          "primaryKey": false,
          "notNull": true,
          "default": "now()"
        }
      },
      "indexes": {
        "idx_positions_status": {
          "name": "idx_positions_status",
          "columns": [
            {
              "expression": "status",
              "isExpression": false,
              "asc": true,
              "nulls": "last"
            }
          ],
          "isUnique": false,
          "concurrently": false,
          "method": "btree",
          "with": {}
        },
        "idx_positions_symbol": {
          "name": "idx_positions_symbol",
          "columns": [
            {
              "expression": "symbol",
              "isExpression": false,
              "asc": true,
              "nulls": "last"
            }
          ],
          "isUnique": false,
          "concurrently": false,
          "method": "btree",
          "with": {}
        }
      },
      "foreignKeys": {},
      "compositePrimaryKeys": {},
      "uniqueConstraints": {},
      "policies": {},
      "checkConstraints": {},
      "isRLSEnabled": false
    },
    "public.signal_deliveries": {
      "name": "signal_deliveries",
      "schema": "",
      "columns": {
        "signal_id": {
          "name": "signal_id",
          "type": "text",
          "primaryKey": true,
          "notNull": true
        },
        "delivery_status": {
          "name": "delivery_status",
          "type": "text",
          "primaryKey": false,
          "notNull": true,
          "default": "'pending'"
        },
        "attempts": {
          "name": "attempts",
          "type": "integer",
          "primaryKey": false,
          "notNull": true,
          "default": 0
        },
        "last_error": {
          "name": "last_error",
          "type": "text",
          "primaryKey": false,
          "notNull": false
        },
        "created_at": {
          "name": "created_at",
          "type": "timestamp with time zone",
          "primaryKey": false,
          "notNull": true,
          "default": "now()"
        }
      },
      "indexes": {
        "idx_deliveries_status": {
          "name": "idx_deliveries_status",
          "columns": [
            {
              "expression": "delivery_status",
              "isExpression": false,
              "asc": true,
              "nulls": "last"
            }
          ],
          "isUnique": false,
          "concurrently": false,
          "method": "btree",
          "with": {}
        }
      },
      "foreignKeys": {},
      "compositePrimaryKeys": {},
      "uniqueConstraints": {},
      "policies": {},
      "checkConstraints": {},
      "isRLSEnabled": false
    },
    "public.signal_outcomes": {
      "name": "signal_outcomes",
      "schema": "",
      "columns": {
        "signal_id": {
          "name": "signal_id",
          "type": "text",
          "primaryKey": false,
          "notNull": true
        },
        "horizon": {
          "name": "horizon",
          "type": "text",
          "primaryKey": false,
          "notNull": true
        },
        "price_at_horizon": {
          "name": "price_at_horizon",
          "type": "double precision",
          "primaryKey": false,
          "notNull": false
        },
        "return_pct": {
          "name": "return_pct",
          "type": "double precision",
          "primaryKey": false,
          "notNull": false
        },
        "benchmark_return_pct": {
          "name": "benchmark_return_pct",
          "type": "double precision",
          "primaryKey": false,
          "notNull": false
        },
        "alpha_pct": {
          "name": "alpha_pct",
          "type": "double precision",
          "primaryKey": false,
          "notNull": false
        },
        "resolved_status": {
          "name": "resolved_status",
          "type": "text",
          "primaryKey": false,
          "notNull": false
        },
        "updated_at": {
          "name": "updated_at",
          "type": "timestamp with time zone",
          "primaryKey": false,
          "notNull": true,
          "default": "now()"
        }
      },
      "indexes": {},
      "foreignKeys": {},
      "compositePrimaryKeys": {
        "signal_outcomes_signal_id_horizon_pk": {
          "name": "signal_outcomes_signal_id_horizon_pk",
          "columns": [
            "signal_id",
            "horizon"
          ]
        }
      },
      "uniqueConstraints": {},
      "policies": {},
      "checkConstraints": {},
      "isRLSEnabled": false
    },
    "public.trading_signals": {
      "name": "trading_signals",
      "schema": "",
      "columns": {
        "id": {
          "name": "id",
          "type": "text",
          "primaryKey": true,
          "notNull": true
        },
        "notification_id": {
          "name": "notification_id",
          "type": "text",
          "primaryKey": false,
          "notNull": false
        },
        "event_id": {
          "name": "event_id",
          "type": "text",
          "primaryKey": false,
          "notNull": false
        },
        "symbol": {
          "name": "symbol",
          "type": "text",
          "primaryKey": false,
          "notNull": true
        },
        "direction": {
          "name": "direction",
          "type": "text",
          "primaryKey": false,
          "notNull": true
        },
        "target_price": {
          "name": "target_price",
          "type": "double precision",
          "primaryKey": false,
          "notNull": false
        },
        "stop_loss": {
          "name": "stop_loss",
          "type": "double precision",
          "primaryKey": false,
          "notNull": false
        },
        "horizon_days": {
          "name": "horizon_days",
          "type": "integer",
          "primaryKey": false,
          "notNull": false
        },
        "conviction": {
          "name": "conviction",
          "type": "text",
          "primaryKey": false,
          "notNull": false
        },
        "entry_price": {
          "name": "entry_price",
          "type": "double precision",
          "primaryKey": false,
          "notNull": false
        },
        "fair_value_base": {
          "name": "fair_value_base",
          "type": "double precision",
          "primaryKey": false,
          "notNull": false
        },
        "deviation_pct": {
          "name": "deviation_pct",
          "type": "double precision",
          "primaryKey": false,
          "notNull": false
        },
        "thesis": {
          "name": "thesis",
          "type": "text",
          "primaryKey": false,
          "notNull": false
        },
        "generated_by": {
          "name": "generated_by",
          "type": "text",
          "primaryKey": false,
          "notNull": false
        },
        "snapshot_id": {
          "name": "snapshot_id",
          "type": "text",
          "primaryKey": false,
          "notNull": false
        },
        "status": {
          "name": "status",
          "type": "text",
          "primaryKey": false,
          "notNull": true
        },
        "created_at": {
          "name": "created_at",
          "type": "timestamp with time zone",
          "primaryKey": false,
          "notNull": true,
          "default": "now()"
        },
        "expires_at": {
          "name": "expires_at",
          "type": "timestamp with time zone",
          "primaryKey": false,
          "notNull": false
        }
      },
      "indexes": {
        "idx_signals_symbol": {
          "name": "idx_signals_symbol",
          "columns": [
            {
              "expression": "symbol",
              "isExpression": false,
              "asc": true,
              "nulls": "last"
            }
          ],
          "isUnique": false,
          "concurrently": false,
          "method": "btree",
          "with": {}
        },
        "uq_signals_notification": {
          "name": "uq_signals_notification",
          "columns": [
            {
              "expression": "notification_id",
              "isExpression": false,
              "asc": true,
              "nulls": "last"
            }
          ],
          "isUnique": true,
          "concurrently": false,
          "method": "btree",
          "with": {}
        },
        "idx_signals_status": {
          "name": "idx_signals_status",
          "columns": [
            {
              "expression": "status",
              "isExpression": false,
              "asc": true,
              "nulls": "last"
            }
          ],
          "isUnique": false,
          "concurrently": false,
          "method": "btree",
          "with": {}
        }
      },
      "foreignKeys": {},
      "compositePrimaryKeys": {},
      "uniqueConstraints": {},
      "policies": {},
      "checkConstraints": {},
      "isRLSEnabled": false
    },
    "public.universe": {
      "name": "universe",
      "schema": "",
      "columns": {
        "symbol": {
          "name": "symbol",
          "type": "text",
          "primaryKey": true,
          "notNull": true
        },
        "name": {
          "name": "name",
          "type": "text",
          "primaryKey": false,
          "notNull": false
        },
        "sector": {
          "name": "sector",
          "type": "text",
          "primaryKey": false,
          "notNull": false
        },
        "industry": {
          "name": "industry",
          "type": "text",
          "primaryKey": false,
          "notNull": false
        },
        "beta": {
          "name": "beta",
          "type": "double precision",
          "primaryKey": false,
          "notNull": false
        },
        "archetype": {
          "name": "archetype",
          "type": "text",
          "primaryKey": false,
          "notNull": false
        },
        "reporting_currency": {
          "name": "reporting_currency",
          "type": "text",
          "primaryKey": false,
          "notNull": false,
          "default": "'USD'"
        },
        "known_at": {
          "name": "known_at",
          "type": "timestamp with time zone",
          "primaryKey": false,
          "notNull": true,
          "default": "now()"
        }
      },
      "indexes": {},
      "foreignKeys": {},
      "compositePrimaryKeys": {},
      "uniqueConstraints": {},
      "policies": {},
      "checkConstraints": {},
      "isRLSEnabled": false
    },
    "public.valuation_snapshots": {
      "name": "valuation_snapshots",
      "schema": "",
      "columns": {
        "snapshot_id": {
          "name": "snapshot_id",
          "type": "text",
          "primaryKey": true,
          "notNull": true
        },
        "symbol": {
          "name": "symbol",
          "type": "text",
          "primaryKey": false,
          "notNull": true
        },
        "as_of": {
          "name": "as_of",
          "type": "date",
          "primaryKey": false,
          "notNull": true
        },
        "fair_value_per_share": {
          "name": "fair_value_per_share",
          "type": "double precision",
          "primaryKey": false,
          "notNull": false
        },
        "current_price": {
          "name": "current_price",
          "type": "double precision",
          "primaryKey": false,
          "notNull": false
        },
        "upside_pct": {
          "name": "upside_pct",
          "type": "double precision",
          "primaryKey": false,
          "notNull": false
        },
        "verdict": {
          "name": "verdict",
          "type": "text",
          "primaryKey": false,
          "notNull": false
        },
        "detail": {
          "name": "detail",
          "type": "jsonb",
          "primaryKey": false,
          "notNull": true
        },
        "code_version": {
          "name": "code_version",
          "type": "text",
          "primaryKey": false,
          "notNull": true
        },
        "created_at": {
          "name": "created_at",
          "type": "timestamp with time zone",
          "primaryKey": false,
          "notNull": true,
          "default": "now()"
        }
      },
      "indexes": {
        "idx_valsnap_symbol": {
          "name": "idx_valsnap_symbol",
          "columns": [
            {
              "expression": "symbol",
              "isExpression": false,
              "asc": true,
              "nulls": "last"
            }
          ],
          "isUnique": false,
          "concurrently": false,
          "method": "btree",
          "with": {}
        }
      },
      "foreignKeys": {},
      "compositePrimaryKeys": {},
      "uniqueConstraints": {},
      "policies": {},
      "checkConstraints": {},
      "isRLSEnabled": false
    },
    "public.watchlist": {
      "name": "watchlist",
      "schema": "",
      "columns": {
        "symbol": {
          "name": "symbol",
          "type": "text",
          "primaryKey": true,
          "notNull": true
        },
        "added_at": {
          "name": "added_at",
          "type": "timestamp with time zone",
          "primaryKey": false,
          "notNull": true,
          "default": "now()"
        }
      },
      "indexes": {},
      "foreignKeys": {},
      "compositePrimaryKeys": {},
      "uniqueConstraints": {},
      "policies": {},
      "checkConstraints": {},
      "isRLSEnabled": false
    }
  },
  "enums": {},
  "schemas": {},
  "sequences": {},
  "roles": {},
  "policies": {},
  "views": {},
  "_meta": {
    "columns": {},
    "schemas": {},
    "tables": {}
  }
}